README.md
setup.py
breezecli/__init__.py
breezecli/cli_progressBar.py
breezecli/login.py
breezecli/main.py
breezecli/utils.py
breezecli.egg-info/PKG-INFO
breezecli.egg-info/SOURCES.txt
breezecli.egg-info/dependency_links.txt
breezecli.egg-info/entry_points.txt
breezecli.egg-info/requires.txt
breezecli.egg-info/top_level.txt